pydancer/__init__.py
pydancer/__main__.py
pydancer/component.py
pydancer/constants.py
pydancer/dancer.py
pydancer/howto.py
pydancer/image_functions.py
pydancer/images.py
pydancer/options.py
pydancer/songs.py
pydancer-0.0.3.dist-info/LICENSE
pydancer-0.0.3.dist-info/METADATA
pydancer-0.0.3.dist-info/WHEEL
pydancer-0.0.3.dist-info/entry_points.txt
pydancer-0.0.3.dist-info/top_level.txt
pydancer-0.0.3.dist-info/RECORD
