Metadata-Version: 2.1
Name: pydancer
Version: 0.0.3
Summary: Python game version of the dance arcade game, using arrow keys to match the steps of the dance.
Author-email: Glenda Boeker <gbb5479@nyu.edu>, Ahmet Ilten <ai2068@nyu.edu>, Shriya Kalakata <sk8812@nyu.edu>, Amber Li <al6862@nyu.edu>
License: GNU GENERAL PUBLIC LICENSE
Project-URL: Repository, https://github.com/software-students-spring2024/3-python-package-exercise-speed
Keywords: python,package,games
Classifier: Programming Language :: Python :: 3
Classifier: Intended Audience :: Education
Classifier: License :: OSI Approved :: GNU General Public License v3 (GPLv3)
Classifier: Operating System :: OS Independent
Requires-Python: >=3.7
License-File: LICENSE
Provides-Extra: dev
Requires-Dist: pytest ; extra == 'dev'
